{
  "version": "7",
  "dialect": "mysql",
  "entries": [
    {
      "idx": 0,
      "version": "5",
      "when": 1771606210565,
      "tag": "0000_mature_namor",
      "breakpoints": true
    },
    {
      "idx": 1,
      "version": "5",
      "when": 1771973012836,
      "tag": "0001_optimal_mindworm",
      "breakpoints": true
    },
    {
      "idx": 2,
      "version": "5",
      "when": 1772544835745,
      "tag": "0002_majestic_carnage",
      "breakpoints": true
    },
    {
      "idx": 3,
      "version": "5",
      "when": 1772660069942,
      "tag": "0003_wonderful_cyclops",
      "breakpoints": true
    }
  ]
}